pokequiz/Classes.py
pokequiz/Question.py
pokequiz/__init__.py
pokequiz/__main__.py
pokequiz/pokequiz.sqlite
pokequiz/seeds.json
pokequiz-1.1.2.dist-info/LICENSE
pokequiz-1.1.2.dist-info/METADATA
pokequiz-1.1.2.dist-info/WHEEL
pokequiz-1.1.2.dist-info/entry_points.txt
pokequiz-1.1.2.dist-info/top_level.txt
pokequiz-1.1.2.dist-info/RECORD
