Metadata-Version: 2.1
Name: pokequiz
Version: 1.1.2
Summary: A command line Pokemon studying tool.
Home-page: https://github.com/Dechrissen/PokeQuiz
Author: Derek Andersen
Author-email: derekcandersen@gmail.com
License: UNKNOWN
Platform: UNKNOWN
Classifier: Programming Language :: Python :: 3
Classifier: License :: OSI Approved :: MIT License
Classifier: Operating System :: OS Independent
Requires-Python: >=3.6
